scystream/__init__.py
scystream-0.0.0.dist-info/METADATA
scystream-0.0.0.dist-info/WHEEL
scystream-0.0.0.dist-info/top_level.txt
scystream-0.0.0.dist-info/RECORD
