Metadata-Version: 2.1
Name: scystream
Version: 0.0.0
Summary: Coming soon
Author-email: Felix Evers <evers@time.rwth-aachen.de>, Paul Kalhorn <kalhorn@time.rwth-aachen.de>
